README.md
setup.py
smartaddress/__init__.py
smartaddress/address.py
smartaddress.egg-info/PKG-INFO
smartaddress.egg-info/SOURCES.txt
smartaddress.egg-info/dependency_links.txt
smartaddress.egg-info/top_level.txt
smartaddress/datas/__init__.py
smartaddress/datas/a1.py
smartaddress/datas/a2.py
smartaddress/datas/a3.py